CMakeLists.txt
LICENSE
MANIFEST.in
README.rst
horovod.exp
horovod.lds
setup.cfg
setup.py
.github/pull_request_template.md
.github/ISSUE_TEMPLATE/bug_report.md
.github/ISSUE_TEMPLATE/feature_request.md
cmake/Utilities.cmake
cmake/build_utils.py
cmake/Modules/FindMxnet.cmake
cmake/Modules/FindNCCL.cmake
cmake/Modules/FindNVTX.cmake
cmake/Modules/FindPytorch.cmake
cmake/Modules/FindROCM.cmake
cmake/Modules/FindTensorflow.cmake
cmake/upstream/FindCUDAToolkit.cmake
docker/README.md
docker/helm/README.md
horovod/__init__.py
horovod.egg-info/PKG-INFO
horovod.egg-info/SOURCES.txt
horovod.egg-info/dependency_links.txt
horovod.egg-info/entry_points.txt
horovod.egg-info/not-zip-safe
horovod.egg-info/requires.txt
horovod.egg-info/top_level.txt
horovod/_keras/__init__.py
horovod/_keras/callbacks.py
horovod/_keras/elastic.py
horovod/common/__init__.py
horovod/common/basics.py
horovod/common/common.cc
horovod/common/common.h
horovod/common/controller.cc
horovod/common/controller.h
horovod/common/elastic.py
horovod/common/exceptions.py
horovod/common/fusion_buffer_manager.cc
horovod/common/fusion_buffer_manager.h
horovod/common/global_state.h
horovod/common/group_table.cc
horovod/common/group_table.h
horovod/common/half.cc
horovod/common/half.h
horovod/common/hashes.h
horovod/common/logging.cc
horovod/common/logging.h
horovod/common/message.cc
horovod/common/message.h
horovod/common/nvtx_op_range.cc
horovod/common/nvtx_op_range.h
horovod/common/operations.cc
horovod/common/operations.h
horovod/common/parameter_manager.cc
horovod/common/parameter_manager.h
horovod/common/process_set.cc
horovod/common/process_set.h
horovod/common/process_sets.py
horovod/common/response_cache.cc
horovod/common/response_cache.h
horovod/common/stall_inspector.cc
horovod/common/stall_inspector.h
horovod/common/tensor_queue.cc
horovod/common/tensor_queue.h
horovod/common/thread_pool.cc
horovod/common/thread_pool.h
horovod/common/timeline.cc
horovod/common/timeline.h
horovod/common/util.py
horovod/common/gloo/gloo_context.cc
horovod/common/gloo/gloo_context.h
horovod/common/gloo/gloo_controller.cc
horovod/common/gloo/gloo_controller.h
horovod/common/gloo/gloo_store.h
horovod/common/gloo/http_store.cc
